sectile/__init__.py
sectile/command_line.py
sectile-0.3.5.dist-info/METADATA
sectile-0.3.5.dist-info/WHEEL
sectile-0.3.5.dist-info/entry_points.txt
sectile-0.3.5.dist-info/top_level.txt
sectile-0.3.5.dist-info/RECORD
