Metadata-Version: 2.1
Name: sectile
Version: 0.3.5
Summary: Multidimensional file stitcher
Home-page: https://github.com/norm/sectile
Author: Mark Norman Francis
Author-email: norm@201created.com
License: MIT
Platform: UNKNOWN
Classifier: Development Status :: 3 - Alpha
Classifier: Intended Audience :: Developers
Classifier: License :: OSI Approved :: MIT License
Classifier: Programming Language :: Python :: 3
Classifier: Topic :: Software Development :: Build Tools
Classifier: Topic :: Software Development :: Code Generators
Classifier: Topic :: Software Development :: Pre-processors
Classifier: Topic :: Text Processing :: Filters
Classifier: Topic :: Text Processing :: General
Requires-Dist: toml
